Metadata-Version: 1.2
Name: BotCrypt
Version: 1.2.1
Summary: crypt and decrypt file
Home-page: https://github.com/botfg/BotCrypt
Author: botfg76
Author-email: botfgbartenevfgzero76@gmail.com
License: Apache License Version 2.0
Platform: UNKNOWN
Classifier: Development Status :: 4 - Beta
Classifier: Programming Language :: Python :: 3 :: Only
Classifier: Environment :: Console
Classifier: License :: OSI Approved :: Apache Software License
Classifier: Operating System :: Unix
Classifier: Topic :: Security :: Cryptography
Requires-Python: >=3.6
